{
    "reg_info": {
        "full_title": "O. Reg. 652/21: AIR POLLUTION - DISCHARGE OF SULPHUR DIOXIDE FROM NICKEL SMELTING AND REFINING FACILITIES IN THE SUDBURY AREA",
        "reg_name_text": "AIR POLLUTION - DISCHARGE OF SULPHUR DIOXIDE FROM NICKEL SMELTING AND REFINING FACILITIES IN THE SUDBURY AREA",
        "citation": "O. Reg. 652/21: ",
        "act_under": "Environmental Protection Act",
        "url": "https://www.ontario.ca/laws/regulation/210652",
        "date_scraped": "2023-12-21 14:53:00"
    },
    "copyright": {
        "Copyright": "© King's Printer for Ontario, 2023."
    },
    "versions": [
        {
            "a_href": "/laws/about-e-laws#ccl",
            "valid_from": "September 17, 2021",
            "valid_to": "current"
        }
    ],
    "content": [
        {
            "ahref_id": "None",
            "TOCid": 1.0,
            "part_id": null,
            "part_type": null,
            "section": "Interpretation",
            "content": NaN,
            "raw_html": NaN
        },
        {
            "ahref_id": "None",
            "TOCid": 2.0,
            "part_id": null,
            "part_type": null,
            "section": "Application",
            "content": NaN,
            "raw_html": NaN
        },
        {
            "ahref_id": "None",
            "TOCid": 3.0,
            "part_id": null,
            "part_type": null,
            "section": "Pyrometallurgical vessels, off-gas collection systems",
            "content": NaN,
            "raw_html": NaN
        },
        {
            "ahref_id": "None",
            "TOCid": 4.0,
            "part_id": null,
            "part_type": null,
            "section": "Pyrometallurgical vessels, pollution control",
            "content": NaN,
            "raw_html": NaN
        },
        {
            "ahref_id": "None",
            "TOCid": 5.0,
            "part_id": null,
            "part_type": null,
            "section": "Single contact acid plants, pollution control",
            "content": NaN,
            "raw_html": NaN
        },
        {
            "ahref_id": "None",
            "TOCid": 6.0,
            "part_id": null,
            "part_type": null,
            "section": "Alternative equivalent methods, request to Director",
            "content": NaN,
            "raw_html": NaN
        },
        {
            "ahref_id": "None",
            "TOCid": 7.0,
            "part_id": null,
            "part_type": null,
            "section": "Alternative equivalent methods plan",
            "content": NaN,
            "raw_html": NaN
        },
        {
            "ahref_id": "None",
            "TOCid": 8.0,
            "part_id": null,
            "part_type": null,
            "section": "Identifying managed sources",
            "content": NaN,
            "raw_html": NaN
        },
        {
            "ahref_id": "None",
            "TOCid": 9.0,
            "part_id": null,
            "part_type": null,
            "section": "Requirement to continue managing sources",
            "content": NaN,
            "raw_html": NaN
        },
        {
            "ahref_id": "None",
            "TOCid": 10.0,
            "part_id": null,
            "part_type": null,
            "section": "Changes re managed sources",
            "content": NaN,
            "raw_html": NaN
        },
        {
            "ahref_id": "None",
            "TOCid": 11.0,
            "part_id": null,
            "part_type": null,
            "section": "Notification, root cause analysis, corrective and preventive actions",
            "content": NaN,
            "raw_html": NaN
        },
        {
            "ahref_id": "None",
            "TOCid": 12.0,
            "part_id": null,
            "part_type": null,
            "section": "Capture efficiency assessment",
            "content": NaN,
            "raw_html": NaN
        },
        {
            "ahref_id": "None",
            "TOCid": 13.0,
            "part_id": null,
            "part_type": null,
            "section": "Action plan, effectiveness report",
            "content": NaN,
            "raw_html": NaN
        },
        {
            "ahref_id": "None",
            "TOCid": 14.0,
            "part_id": null,
            "part_type": null,
            "section": "Management measures, effectiveness report",
            "content": NaN,
            "raw_html": NaN
        },
        {
            "ahref_id": "None",
            "TOCid": 15.0,
            "part_id": null,
            "part_type": null,
            "section": "Summary reports",
            "content": NaN,
            "raw_html": NaN
        },
        {
            "ahref_id": "None",
            "TOCid": 16.0,
            "part_id": null,
            "part_type": null,
            "section": "Retention of records, etc.",
            "content": NaN,
            "raw_html": NaN
        },
        {
            "ahref_id": "None",
            "TOCid": 17.0,
            "part_id": null,
            "part_type": null,
            "section": "Compliance with notice",
            "content": NaN,
            "raw_html": NaN
        },
        {
            "ahref_id": "None",
            "TOCid": 18.0,
            "part_id": null,
            "part_type": null,
            "section": "Form of submissions",
            "content": NaN,
            "raw_html": NaN
        }
    ]
}