{
    "reg_info": {
        "full_title": "O. Reg. 338/02: NON-APPLICATION OF PART III OF THE MUNICIPAL AFFAIRS ACT",
        "reg_name_text": "NON-APPLICATION OF PART III OF THE MUNICIPAL AFFAIRS ACT",
        "citation": "O. Reg. 338/02: ",
        "act_under": "Town of Moosonee Act, 2000   Loi de 2000 sur la ville de Moosonee",
        "url": "https://www.ontario.ca/laws/regulation/020338",
        "date_scraped": "2023-12-19 21:42:23"
    },
    "copyright": {
        "Copyright": "© King's Printer for Ontario, 2023."
    },
    "versions": [
        {
            "a_href": "/laws/about-e-laws#ccl",
            "valid_from": "January  1, 2003",
            "valid_to": "current"
        }
    ],
    "content": [
        {
            "id": "1.",
            "section": "Non-application",
            "content": "1. For the purposes of section 5 of the Act, Part III of the Municipal Affairs Act ceases to apply to the Town of Moosonee. O. Reg. 338/02, s. 1.",
            "raw_html": "<p class=\"section-e\"><b>1. </b>For the purposes of section 5 of the Act, Part III of the <i>Municipal Affairs Act</i> ceases to apply to the Town of Moosonee. O. Reg. 338/02, s. 1.</p>"
        },
        {
            "id": "2.",
            "section": "Non-application",
            "content": "2. Omitted (provides for coming into force of provisions of this Regulation). O. Reg. 338/02, s. 2. ",
            "raw_html": "<p class=\"section-e\"><b>2.</b> Omitted (provides for coming into force of provisions of this Regulation). O. Reg. 338/02, s. 2.</p> <p class=\"Normal\"></p>"
        }
    ]
}