{
    "reg_info": {
        "full_title": "O. Reg. 20/10: FEES FOR NON-PERMANENT RESIDENTS - EXEMPTIONS",
        "reg_name_text": "fees for non-permanent residents — exemptions",
        "citation": "O. Reg. 20/10: FEES FOR NON-PERMANENT RESIDENTS - EXEMPTIONS",
        "act_under": "Education Act",
        "url": "https://www.ontario.ca/laws/regulation/100020",
        "date_scraped": "2023-12-18 03:28:58"
    },
    "copyright": {
        "Copyright": "© King's Printer for Ontario, 2023."
    },
    "versions": [
        {
            "a_href": "/laws/about-e-laws#ccl",
            "valid_from": "August 18, 2023",
            "valid_to": "current"
        },
        {
            "a_href": "/laws/regulation/100020/v5",
            "valid_from": "April  6, 2022",
            "valid_to": "August 17, 2023"
        },
        {
            "a_href": "/laws/regulation/100020/v4",
            "valid_from": "October 29, 2019",
            "valid_to": "April  5, 2022"
        },
        {
            "a_href": "/laws/regulation/100020/v3",
            "valid_from": "May  4, 2011",
            "valid_to": "October 28, 2019"
        },
        {
            "a_href": "/laws/regulation/100020/v2",
            "valid_from": "October 12, 2010",
            "valid_to": "May  3, 2011"
        },
        {
            "a_href": "/laws/regulation/100020/v1",
            "valid_from": "February 10, 2010",
            "valid_to": "October 11, 2010"
        },
        {
            "a_href": "#",
            "valid_from": "N/A",
            "valid_to": "current"
        }
    ],
    "content": [
        {
            "id": "1.",
            "section": "Prescribed class",
            "content": " 1. Each of the following classes is prescribed as a class for which a board shall not charge a fee in accordance with subsection 49 (7) of the Act: 1.  Persons who, i.  were displaced as a result of Hurricane Katrina, and ii.  were admitted to a school of a board in the 2005-2006 school year. 2.  Persons who, i.  were displaced as a result of the 2010 earthquake in Haiti, and ii.  were admitted to a school of a board in the 2009-2010 school year or in the 2010-2011 school year. 3.  Persons who, i.  were displaced as a result of the March 2011 earthquake or tsunami in Japan, and ii.  were admitted to a school of the board in the 2010-2011 school year or in the 2011-2012 school year. 4.  Persons who, i.  were displaced as a result of Hurricane Dorian, and ii.  were admitted to a school of the board in the 2019-2020 school year. 5.  Persons who, i.  were granted an emergency authorization to enter into or remain in Canada for humanitarian reasons, and ii.  are in Canada under that authorization. O. Reg. 20/10, s. 1; O. Reg. 388/10, s. 1; O. Reg. 133/11, s. 1; O. Reg. 356/19, s. 1; O. Reg. 301/22, s. 1; O. Reg. 265/23, s. 1.",
            "raw_html": "<p class=\"section-e\"> <b>1. </b>Each of the following classes is prescribed as a class for which a board shall not charge a fee in accordance with subsection 49 (7) of the Act:</p> <p class=\"paragraph-e\">  1.  Persons who,</p> <p class=\"subpara-e\">  i.  were displaced as a result of Hurricane Katrina, and</p> <p class=\"subpara-e\">  ii.  were admitted to a school of a board in the 2005-2006 school year.</p> <p class=\"paragraph-e\">  2.  Persons who,</p> <p class=\"subpara-e\">  i.  were displaced as a result of the 2010 earthquake in Haiti, and</p> <p class=\"subpara-e\">  ii.  were admitted to a school of a board in the 2009-2010 school year or in the 2010-2011 school year.</p> <p class=\"paragraph-e\">  3.  Persons who,</p> <p class=\"subpara-e\">  i.  were displaced as a result of the March 2011 earthquake or tsunami in Japan, and</p> <p class=\"subpara-e\">  ii.  were admitted to a school of the board in the 2010-2011 school year or in the 2011-2012 school year.</p> <p class=\"paragraph-e\">  4.  Persons who,</p> <p class=\"subpara-e\">  i.  were displaced as a result of Hurricane Dorian, and</p> <p class=\"subpara-e\">  ii.  were admitted to a school of the board in the 2019-2020 school year.</p> <p class=\"paragraph-e\">  5.  Persons who,</p> <p class=\"subpara-e\">  i.  were granted an emergency authorization to enter into or remain in Canada for humanitarian reasons, and</p> <p class=\"subpara-e\">  ii.  are in Canada under that authorization. O. Reg. 20/10, s. 1; O. Reg. 388/10, s. 1; O. Reg. 133/11, s. 1; O. Reg. 356/19, s. 1; O. Reg. 301/22, s. 1; O. Reg. 265/23, s. 1.</p>"
        },
        {
            "id": "2.",
            "section": "Prescribed class",
            "content": " 2. Omitted (revokes other Regulations). O. Reg. 20/10, s. 2.",
            "raw_html": "<p class=\"section-e\"> <b>2.</b> <span class=\"ovsmallcap\">Omitted</span> (<span class=\"ovsmallcap\">revokes other Regulations</span>). O. Reg. 20/10, s. 2.</p>"
        },
        {
            "id": "3.",
            "section": "Prescribed class",
            "content": " 3. Omitted (provides for coming into force of provisions of this Regulation). O. Reg. 20/10, s. 3.",
            "raw_html": "<p class=\"section-e\"> <b>3.</b> <span class=\"ovsmallcap\">Omitted</span> (<span class=\"ovsmallcap\">provides for coming into force of provisions of this Regulation</span>). O. Reg. 20/10, s. 3.</p>"
        },
        {
            "id": null,
            "section": "Prescribed class",
            "content": "  Français  ",
            "raw_html": "<p class=\"section-e\"> </p> <p class=\"MsoNormal\"><a href=\"http://www.ontario.ca/fr/lois/reglement/100020\">Français</a></p> <p class=\"MsoNormal\"> </p> <p class=\"MsoNormal\"></p>"
        }
    ]
}