{
    "act_info": {
        "full_title": "Ontario Loan Act, 2015, S.O. 2015, c. 20, Sched. 32",
        "act_name_text": "Not Found",
        "citation": "Ontario Loan Act, 2015, S.O. 2015, c. 20, Sched. 32",
        "url": "https://www.ontario.ca/laws/statute/15o20a",
        "date_scraped": "2023-12-19 03:46:58"
    },
    "copyright": {
        "Copyright": "© King's Printer for Ontario, 2023."
    },
    "versions": [
        {
            "a_href": "/laws/about-e-laws#ccl",
            "valid_from": "September  2, 2015",
            "valid_to": "current"
        },
        {
            "a_href": "/laws/statute/15o20a/v1",
            "valid_from": "June  4, 2015",
            "valid_to": "September  1, 2015"
        }
    ],
    "current_regs": [],
    "revoked_regs": [],
    "content": [
        {
            "id": "s1s1",
            "section": "Borrowing authorized",
            "content": " 1. (1) The Lieutenant Governor in Council may borrow in any manner provided by the Financial Administration Act such sums, not exceeding a total aggregate amount of $14.7 billion as are considered necessary to discharge any indebtedness or obligation of Ontario or to make any payment authorized or required by any Act to be made out of the Consolidated Revenue Fund. Other Acts (2) The authority to borrow conferred by this Act is in addition to that conferred by any other Act.",
            "raw_html": "<p class=\"section-e\"><a name=\"s1s1\"></a> <a href=\"http://www.ontario.ca/fr/lois/loi/15o20a#s1s1\"><span lang=\"EN-US\">1. (1)</span></a> The Lieutenant Governor in Council may borrow in any manner provided by the <i>Financial Administration Act</i> such sums, not exceeding a total aggregate amount of $14.7<b> </b>billion as are considered necessary to discharge any indebtedness or obligation of Ontario or to make any payment authorized or required by any Act to be made out of the Consolidated Revenue Fund.</p> <p class=\"headnote-e\">Other Acts</p> <p class=\"subsection-e\"><a name=\"s1s2\"></a> <a href=\"http://www.ontario.ca/fr/lois/loi/15o20a#s1s2\"><span lang=\"EN-US\">(2)</span></a> The authority to borrow conferred by this Act is in addition to that conferred by any other Act.</p>"
        },
        {
            "id": "s2s1",
            "section": "Expiry",
            "content": " 2. (1) No order in council authorizing borrowing authorized under this Act shall be made after December 31, 2017. Same (2) The Crown shall not borrow money after December 31, 2018 under the authority of an order in council that authorizes borrowing under this Act unless, on or before December 31, 2018, (a) the Crown has entered into an agreement to borrow the money under the order in council; or (b) the Crown has entered into an agreement respecting a borrowing program and the agreement enables the Crown to borrow up to a specified limit under the order in council. 3. Omitted\r\n(provides for coming into force of provisions of this Act). 4. Omitted (enacts short title of this Act). ______________  Français  ",
            "raw_html": "<p class=\"section-e\"><a name=\"s2s1\"></a> <a href=\"http://www.ontario.ca/fr/lois/loi/15o20a#s2s1\"><span lang=\"EN-US\">2. (1)</span></a> No order in council authorizing borrowing authorized under this Act shall be made after December 31, 2017.</p> <p class=\"headnote-e\">Same</p> <p class=\"subsection-e\"><a name=\"s2s2\"></a> <a href=\"http://www.ontario.ca/fr/lois/loi/15o20a#s2s2\"><span lang=\"EN-US\">(2)</span></a> The Crown shall not borrow money after December 31, 2018 under the authority of an order in council that authorizes borrowing under this Act unless, on or before December 31, 2018,</p> <p class=\"clause-e\">  (a) the Crown has entered into an agreement to borrow the money under the order in council; or</p> <p class=\"clause-e\">  (b) the Crown has entered into an agreement respecting a borrowing program and the agreement enables the Crown to borrow up to a specified limit under the order in council.</p> <p class=\"section-e\"><a name=\"s3\"></a> <a href=\"http://www.ontario.ca/fr/lois/loi/15o20a#s3\"><span lang=\"EN-US\">3.</span></a> <span class=\"ovsmallcap\">Omitted</span>\r\n(<span class=\"ovsmallcap\">provides for coming into force of provisions of this Act</span>).</p> <p class=\"section-e\"><a name=\"s4\"></a> <a href=\"http://www.ontario.ca/fr/lois/loi/15o20a#s4\"><span lang=\"EN-US\">4.</span></a> <span class=\"ovsmallcap\">Omitted (enacts short title of this Act).</span></p> <p class=\"line-e\">______________</p> <p class=\"line-e\"> </p> <p class=\"MsoNormal\"><a href=\"http://www.ontario.ca/fr/lois/loi/15o20a\">Français</a></p> <p class=\"MsoNormal\"> </p> <p class=\"MsoNormal\"></p>"
        },
        {
            "id": "s3",
            "section": "Same",
            "content": " 3. Omitted\r\n(provides for coming into force of provisions of this Act). 4. Omitted (enacts short title of this Act). ______________  Français  ",
            "raw_html": "<p class=\"section-e\"><a name=\"s3\"></a> <a href=\"http://www.ontario.ca/fr/lois/loi/15o20a#s3\"><span lang=\"EN-US\">3.</span></a> <span class=\"ovsmallcap\">Omitted</span>\r\n(<span class=\"ovsmallcap\">provides for coming into force of provisions of this Act</span>).</p> <p class=\"section-e\"><a name=\"s4\"></a> <a href=\"http://www.ontario.ca/fr/lois/loi/15o20a#s4\"><span lang=\"EN-US\">4.</span></a> <span class=\"ovsmallcap\">Omitted (enacts short title of this Act).</span></p> <p class=\"line-e\">______________</p> <p class=\"line-e\"> </p> <p class=\"MsoNormal\"><a href=\"http://www.ontario.ca/fr/lois/loi/15o20a\">Français</a></p> <p class=\"MsoNormal\"> </p> <p class=\"MsoNormal\"></p>"
        },
        {
            "id": "s4",
            "section": "Same",
            "content": " 4. Omitted (enacts short title of this Act). ______________  Français  ",
            "raw_html": "<p class=\"section-e\"><a name=\"s4\"></a> <a href=\"http://www.ontario.ca/fr/lois/loi/15o20a#s4\"><span lang=\"EN-US\">4.</span></a> <span class=\"ovsmallcap\">Omitted (enacts short title of this Act).</span></p> <p class=\"line-e\">______________</p> <p class=\"line-e\"> </p> <p class=\"MsoNormal\"><a href=\"http://www.ontario.ca/fr/lois/loi/15o20a\">Français</a></p> <p class=\"MsoNormal\"> </p> <p class=\"MsoNormal\"></p>"
        }
    ]
}